safeoutput/__init__.py
safeoutput-3.0.dist-info/licenses/LICENSE
safeoutput-3.0.dist-info/METADATA
safeoutput-3.0.dist-info/WHEEL
safeoutput-3.0.dist-info/entry_points.txt
safeoutput-3.0.dist-info/top_level.txt
safeoutput-3.0.dist-info/zip-safe
safeoutput-3.0.dist-info/RECORD
