Metadata-Version: 2.4
Name: safeoutput
Version: 3.0
Summary: Tempfile wrapper to ensure output files are either complete, or empty. Also handles stdout, which gives no truncation guarantees.
Author-email: andrew thomson <athomsonguy@gmail.com>
License-Expression: MIT
Project-URL: Homepage, http://github.com/andrewguy9/safeoutput
Classifier: Development Status :: 5 - Production/Stable
Classifier: Topic :: Software Development :: Libraries
Classifier: Topic :: System :: Filesystems
Classifier: Programming Language :: Python :: 3.8
Classifier: Programming Language :: Python :: 3.9
Classifier: Programming Language :: Python :: 3.10
Classifier: Programming Language :: Python :: 3.11
Classifier: Programming Language :: Python :: 3.12
Requires-Python: >=3.8
License-File: LICENSE
Provides-Extra: test
Requires-Dist: pytest; extra == "test"
Provides-Extra: dev
Requires-Dist: mypy; extra == "dev"
Requires-Dist: pytest; extra == "dev"
Dynamic: license-file
